hypervecs/__init__.py
hypervecs/embeddings.py
hypervecs/funcs.py
hypervecs/functional.py
hypervecs/hypervector.py
hypervecs/ml.py
hypervecs/types.py
hypervecs-0.0.1.dist-info/LICENSE
hypervecs-0.0.1.dist-info/METADATA
hypervecs-0.0.1.dist-info/WHEEL
hypervecs-0.0.1.dist-info/entry_points.txt
hypervecs-0.0.1.dist-info/RECORD
